guillotina_asyncom/__init__.py
guillotina_asyncom/db.py
guillotina_asyncom/interfaces.py
guillotina_asyncom/serializers.py
guillotina_asyncom/utils.py
guillotina_asyncom/content/__init__.py
guillotina_asyncom/services/__init__.py
guillotina_asyncom/services/base.py
guillotina_asyncom/services/crud.py
guillotina_asyncom/services/search.py
guillotina_asyncom/tests/__init__.py
guillotina_asyncom/tests/conftest.py
guillotina_asyncom/tests/data.py
guillotina_asyncom/tests/fixtures.py
guillotina_asyncom/tests/test_basic.py
guillotina_asyncom/tests/utils.py
guillotina_asyncom/utilities/__init__.py
guillotina_asyncom/utilities/om.py
guillotina_asyncom-0a1.dist-info/METADATA
guillotina_asyncom-0a1.dist-info/WHEEL
guillotina_asyncom-0a1.dist-info/top_level.txt
guillotina_asyncom-0a1.dist-info/RECORD
