Metadata-Version: 2.1
Name: guillotina-asyncom
Version: 0a1
Summary: Guillotina Postgresql integration
Home-page: https://github.com/jordic/guillotina_asyncom
Author: Jordi Collell
Author-email: jordic@gmail.com
License: BSD
Keywords: asyncio,REST,Framework,transactional,asgi,postgresql,sqlalchemy
Platform: UNKNOWN
Classifier: License :: OSI Approved :: BSD License
Classifier: Intended Audience :: Developers
Classifier: Topic :: Internet :: WWW/HTTP
Classifier: Programming Language :: Python :: 3.7
Classifier: Programming Language :: Python :: 3.8
Classifier: Topic :: Software Development :: Libraries :: Python Modules
Requires-Python: >=3.7.0
Requires-Dist: guillotina
Requires-Dist: asyncom (>=0.3.1)
Provides-Extra: test
Requires-Dist: pytest (>=3.8.0<=5.0.0) ; extra == 'test'
Requires-Dist: docker ; extra == 'test'
Requires-Dist: backoff ; extra == 'test'
Requires-Dist: psycopg2-binary ; extra == 'test'
Requires-Dist: pytest-asyncio (>=0.10.0) ; extra == 'test'
Requires-Dist: pytest-cov ; extra == 'test'
Requires-Dist: coverage (>=4.0.3) ; extra == 'test'
Requires-Dist: pytest-docker-fixtures ; extra == 'test'
Requires-Dist: pytest-rerunfailures (<=7.0) ; extra == 'test'
Requires-Dist: async-asgi-testclient (~=1.2.0) ; extra == 'test'
